dialects/__init__.py
dialects/activate.py
dialects/importer.py
dialects/util.py
lispython/__init__.py
listhell/__init__.py
pydialect-0.1.1.data/data/LICENSE.md
pydialect-0.1.1.data/data/README.md
pydialect-0.1.1.data/scripts/pydialect
pydialect-0.1.1.dist-info/METADATA
pydialect-0.1.1.dist-info/RECORD
pydialect-0.1.1.dist-info/WHEEL
pydialect-0.1.1.dist-info/top_level.txt
pytkell/__init__.py
