Metadata-Version: 2.1
Name: pydialect
Version: 0.1.1
Summary: Build languages on Python.
Home-page: https://github.com/Technologicat/pydialect
Author: Juha Jeronen
Author-email: juha.m.jeronen@gmail.com
License: BSD
Keywords: metaprogramming,programming-language-development,dialects
Platform: Linux
Classifier: Development Status :: 4 - Beta
Classifier: Environment :: Console
Classifier: Intended Audience :: Developers
Classifier: License :: OSI Approved :: BSD License
Classifier: Operating System :: POSIX :: Linux
Classifier: Programming Language :: Python
Classifier: Programming Language :: Python :: 3
Classifier: Programming Language :: Python :: 3.4
Classifier: Topic :: Software Development :: Libraries
Classifier: Topic :: Software Development :: Libraries :: Python Modules
Provides: pydialect
Provides: dialects
Provides: lispython
